{
  "reports": [
    {
      "M": 0,
      "Moneypenny": 0,
      "agentsSerialNumbers": [
        "003"
      ],
      "agentsNames": [
        "King Jellybean"
      ],
      "gadgetName": "Neutrino bomb2",
      "timeIssued": 2,
      "QTime": 2,
      "timeCreated": 2
    },
    {
      "M": 1,
      "Moneypenny": 1,
      "agentsSerialNumbers": [
        "001",
        "002"
      ],
      "agentsNames": [
        "Mr. Goldenfold",
        "Jerry Smith"
      ],
      "gadgetName": "Laser Gun",
      "timeIssued": 3,
      "QTime": 4,
      "timeCreated": 3
    },
    {
      "M": 2,
      "Moneypenny": 2,
      "agentsSerialNumbers": [
        "001"
      ],
      "agentsNames": [
        "Mr. Goldenfold"
      ],
      "gadgetName": "Interdimensional cable TV box2",
      "timeIssued": 3,
      "QTime": 14,
      "timeCreated": 3
    },
    {
      "M": 7,
      "Moneypenny": 7,
      "agentsSerialNumbers": [
        "002",
        "003"
      ],
      "agentsNames": [
        "Jerry Smith",
        "King Jellybean"
      ],
      "gadgetName": "Portal gun2",
      "timeIssued": 14,
      "QTime": 14,
      "timeCreated": 14
    },
    {
      "M": 6,
      "Moneypenny": 6,
      "agentsSerialNumbers": [
        "002",
        "003"
      ],
      "agentsNames": [
        "Jerry Smith",
        "King Jellybean"
      ],
      "gadgetName": "Ionic Defibulizer",
      "timeIssued": 14,
      "QTime": 22,
      "timeCreated": 14
    },
    {
      "M": 8,
      "Moneypenny": 0,
      "agentsSerialNumbers": [
        "001",
        "002"
      ],
      "agentsNames": [
        "Mr. Goldenfold",
        "Jerry Smith"
      ],
      "gadgetName": "Microverse battery3",
      "timeIssued": 15,
      "QTime": 29,
      "timeCreated": 15
    },
    {
      "M": 3,
      "Moneypenny": 3,
      "agentsSerialNumbers": [
        "001",
        "003"
      ],
      "agentsNames": [
        "Mr. Goldenfold",
        "King Jellybean"
      ],
      "gadgetName": "Emergency Bionic Arm2",
      "timeIssued": 6,
      "QTime": 29,
      "timeCreated": 6
    },
    {
      "M": 9,
      "Moneypenny": 1,
      "agentsSerialNumbers": [
        "001"
      ],
      "agentsNames": [
        "Mr. Goldenfold"
      ],
      "gadgetName": "Portal gun3",
      "timeIssued": 24,
      "QTime": 43,
      "timeCreated": 24
    },
    {
      "M": 5,
      "Moneypenny": 5,
      "agentsSerialNumbers": [
        "000",
        "002"
      ],
      "agentsNames": [
        "Arthricia",
        "Jerry Smith"
      ],
      "gadgetName": "Microverse battery",
      "timeIssued": 12,
      "QTime": 43,
      "timeCreated": 12
    }
  ],
  "total": 19
}