{
  "reports": [
    {
      "missionName": "You\u0027re like Hitler, except...Hitler cared about Germany, or something.",
      "M": 0,
      "Moneypenny": 0,
      "agentsSerialNumbers": [
        "001"
      ],
      "agentsNames": [
        "Mr. Goldenfold"
      ],
      "gadgetName": "Interdimensional Goggles",
      "timeIssued": 1,
      "QTime": 1,
      "timeCreated": 1
    },
    {
      "missionName": "Yo! What up my glip glops!",
      "M": 1,
      "Moneypenny": 1,
      "agentsSerialNumbers": [
        "000",
        "001"
      ],
      "agentsNames": [
        "Tiny Rick",
        "Mr. Goldenfold"
      ],
      "gadgetName": "Cognition amplifier",
      "timeIssued": 2,
      "QTime": 2,
      "timeCreated": 2
    },
    {
      "missionName": "You\u0027re like Hitler, except...Hitler cared about Germany, or something.",
      "M": 2,
      "Moneypenny": 0,
      "agentsSerialNumbers": [
        "001"
      ],
      "agentsNames": [
        "Mr. Goldenfold"
      ],
      "gadgetName": "Emergency Bionic Arm",
      "timeIssued": 3,
      "QTime": 3,
      "timeCreated": 3
    },
    {
      "missionName": "That just sounds like slavery with extra steps.",
      "M": 3,
      "Moneypenny": 1,
      "agentsSerialNumbers": [
        "001"
      ],
      "agentsNames": [
        "Mr. Goldenfold"
      ],
      "gadgetName": "Time freezer",
      "timeIssued": 3,
      "QTime": 3,
      "timeCreated": 3
    },
    {
      "missionName": "HI! I\u0027M MR MEESEEKS! LOOK AT ME!",
      "M": 0,
      "Moneypenny": 0,
      "agentsSerialNumbers": [
        "000",
        "001"
      ],
      "agentsNames": [
        "Tiny Rick",
        "Mr. Goldenfold"
      ],
      "gadgetName": "Cognition amplifier",
      "timeIssued": 4,
      "QTime": 4,
      "timeCreated": 4
    },
    {
      "missionName": "Pluto\u0027s a planet.",
      "M": 1,
      "Moneypenny": 1,
      "agentsSerialNumbers": [
        "001"
      ],
      "agentsNames": [
        "Mr. Goldenfold"
      ],
      "gadgetName": "Shrink ray",
      "timeIssued": 5,
      "QTime": 5,
      "timeCreated": 5
    },
    {
      "missionName": "He\u0027s not a hot girl. He can\u0027t just bail on his life and set up shop in someone else\u0027s.",
      "M": 3,
      "Moneypenny": 1,
      "agentsSerialNumbers": [
        "001"
      ],
      "agentsNames": [
        "Mr. Goldenfold"
      ],
      "gadgetName": "Microverse battery2",
      "timeIssued": 6,
      "QTime": 18,
      "timeCreated": 6
    },
    {
      "missionName": "Uncertainty is inherently unsustainable. Eventually, everything either is or isn\u0027t.",
      "M": 1,
      "Moneypenny": 1,
      "agentsSerialNumbers": [
        "000"
      ],
      "agentsNames": [
        "Tiny Rick"
      ],
      "gadgetName": "Dream inceptor",
      "timeIssued": 7,
      "QTime": 18,
      "timeCreated": 7
    },
    {
      "missionName": "No no, If I wanted to be sober, I wouldn’t have gotten drunk.",
      "M": 2,
      "Moneypenny": 0,
      "agentsSerialNumbers": [
        "000",
        "001"
      ],
      "agentsNames": [
        "Tiny Rick",
        "Mr. Goldenfold"
      ],
      "gadgetName": "Dream inceptor",
      "timeIssued": 5,
      "QTime": 18,
      "timeCreated": 5
    },
    {
      "missionName": "You\u0027re our boy dog, don\u0027t even trip.",
      "M": 0,
      "Moneypenny": 0,
      "agentsSerialNumbers": [
        "001"
      ],
      "agentsNames": [
        "Mr. Goldenfold"
      ],
      "gadgetName": "Purge Suit",
      "timeIssued": 6,
      "QTime": 18,
      "timeCreated": 6
    },
    {
      "missionName": "There is no god, Summer; gotta rip that band-aid off now you\u0027ll thank me later.",
      "M": 3,
      "Moneypenny": 0,
      "agentsSerialNumbers": [
        "000",
        "002"
      ],
      "agentsNames": [
        "Tiny Rick",
        "Scary Terry"
      ],
      "gadgetName": "Dark matter",
      "timeIssued": 11,
      "QTime": 18,
      "timeCreated": 11
    },
    {
      "missionName": "This isn\u0027t Game of Thrones, Morty.",
      "M": 1,
      "Moneypenny": 1,
      "agentsSerialNumbers": [
        "000",
        "001"
      ],
      "agentsNames": [
        "Tiny Rick",
        "Mr. Goldenfold"
      ],
      "gadgetName": "Emergency Bionic Arm",
      "timeIssued": 14,
      "QTime": 18,
      "timeCreated": 14
    },
    {
      "missionName": "Uncertainty is inherently unsustainable. Eventually, everything either is or isn\u0027t.",
      "M": 0,
      "Moneypenny": 1,
      "agentsSerialNumbers": [
        "000",
        "002"
      ],
      "agentsNames": [
        "Tiny Rick",
        "Scary Terry"
      ],
      "gadgetName": "Purge Suit",
      "timeIssued": 13,
      "QTime": 18,
      "timeCreated": 13
    },
    {
      "missionName": "Existence is pain to a meeseeks Jerry, and we will do anything to alleviate that pain.",
      "M": 2,
      "Moneypenny": 0,
      "agentsSerialNumbers": [
        "000",
        "001"
      ],
      "agentsNames": [
        "Tiny Rick",
        "Mr. Goldenfold"
      ],
      "gadgetName": "Shrink ray",
      "timeIssued": 8,
      "QTime": 18,
      "timeCreated": 8
    }
  ],
  "total": 18
}