{
  "reports": [
    {
      "M": 1,
      "Moneypenny": 0,
      "agentsSerialNumbers": [
        "003",
        "004"
      ],
      "agentsNames": [
        "Jessica",
        "Tammy Gueterman"
      ],
      "gadgetName": "Purge Suit",
      "timeIssued": 1,
      "QTime": 1,
      "timeCreated": 1
    },
    {
      "M": 2,
      "Moneypenny": 1,
      "agentsSerialNumbers": [
        "004"
      ],
      "agentsNames": [
        "Tammy Gueterman"
      ],
      "gadgetName": "Cognition amplifier",
      "timeIssued": 2,
      "QTime": 5,
      "timeCreated": 2
    },
    {
      "M": 8,
      "Moneypenny": 1,
      "agentsSerialNumbers": [
        "000",
        "002",
        "006"
      ],
      "agentsNames": [
        "Krombopulos Michael",
        "Morty Smith",
        "Squanchy"
      ],
      "gadgetName": "Grappling Shoes3",
      "timeIssued": 16,
      "QTime": 20,
      "timeCreated": 16
    },
    {
      "M": 6,
      "Moneypenny": 5,
      "agentsSerialNumbers": [
        "001",
        "003",
        "005"
      ],
      "agentsNames": [
        "Eyeholes Man",
        "Jessica",
        "Unity"
      ],
      "gadgetName": "Shrink ray2",
      "timeIssued": 8,
      "QTime": 20,
      "timeCreated": 8
    },
    {
      "M": 5,
      "Moneypenny": 4,
      "agentsSerialNumbers": [
        "004"
      ],
      "agentsNames": [
        "Tammy Gueterman"
      ],
      "gadgetName": "Laser Gun",
      "timeIssued": 7,
      "QTime": 33,
      "timeCreated": 7
    },
    {
      "M": 2,
      "Moneypenny": 5,
      "agentsSerialNumbers": [
        "001",
        "005"
      ],
      "agentsNames": [
        "Eyeholes Man",
        "Unity"
      ],
      "gadgetName": "Portal gun2",
      "timeIssued": 17,
      "QTime": 33,
      "timeCreated": 17
    },
    {
      "M": 0,
      "Moneypenny": 2,
      "agentsSerialNumbers": [
        "001",
        "002",
        "003"
      ],
      "agentsNames": [
        "Eyeholes Man",
        "Morty Smith",
        "Jessica"
      ],
      "gadgetName": "Combat suit",
      "timeIssued": 11,
      "QTime": 33,
      "timeCreated": 11
    },
    {
      "M": 3,
      "Moneypenny": 3,
      "agentsSerialNumbers": [
        "002",
        "004"
      ],
      "agentsNames": [
        "Morty Smith",
        "Tammy Gueterman"
      ],
      "gadgetName": "Demonic Alien Containment Box",
      "timeIssued": 13,
      "QTime": 43,
      "timeCreated": 13
    }
  ],
  "total": 17
}